Metadata-Version: 2.1
Name: rdb_json_parser
Version: 0.4
Author: Nikunj Pathak
Author-email: nik.twister@gmail.com
License-File: LICENSE.txt
